byte/__init__.py
byte/compilers/__init__.py
byte/compilers/sqlite/__init__.py
byte/compilers/sqlite/base.py
byte/compilers/sqlite/insert.py
byte/compilers/sqlite/main.py
byte/compilers/sqlite/select.py
byte/compilers/sqlite/models/__init__.py
byte/compilers/sqlite/models/clause.py
byte/compilers/sqlite/models/entity.py
byte/compilers/sqlite/models/expressions.py
byte/compilers/sqlite/models/set.py
byte/executors/__init__.py
byte/executors/sqlite/__init__.py
byte/executors/sqlite/main.py
byte/executors/sqlite/tasks.py
byte/executors/sqlite/models/__init__.py
byte/executors/sqlite/models/connection.py
byte/executors/sqlite/models/cursor.py
byte/executors/sqlite/models/transaction.py
byte_sqlite-0.3.1.dist-info/DESCRIPTION.rst
byte_sqlite-0.3.1.dist-info/METADATA
byte_sqlite-0.3.1.dist-info/RECORD
byte_sqlite-0.3.1.dist-info/WHEEL
byte_sqlite-0.3.1.dist-info/metadata.json
byte_sqlite-0.3.1.dist-info/pbr.json
byte_sqlite-0.3.1.dist-info/top_level.txt
